{
  "2ndstreet": [
    "2026-06-28",
    "2026-06-29",
    "2026-06-30",
    "2026-07-01"
  ],
  "bookoff": [
    "2026-06-28",
    "2026-06-29",
    "2026-06-30",
    "2026-07-01"
  ],
  "dosupara": [
    "2026-06-28",
    "2026-06-29",
    "2026-06-30",
    "2026-07-01"
  ],
  "geo": [],
  "geo_mobile": [
    "2026-06-28",
    "2026-06-29",
    "2026-06-30",
    "2026-07-01"
  ],
  "hardoff": [
    "2026-06-28",
    "2026-06-29",
    "2026-06-30",
    "2026-07-01"
  ],
  "iosys": [],
  "janpara": [
    "2026-06-28",
    "2026-06-29",
    "2026-06-30",
    "2026-07-01"
  ],
  "kaitori_itchome": [],
  "kaitori_shouten": [],
  "mobile_ichiban": [],
  "netoff": [],
  "pasoko": [
    "2026-06-28",
    "2026-06-29",
    "2026-06-30",
    "2026-07-01"
  ],
  "sofmap": [
    "2026-06-28",
    "2026-06-29",
    "2026-06-30",
    "2026-07-01"
  ],
  "surugaya": [
    "2026-06-28",
    "2026-06-29",
    "2026-06-30",
    "2026-07-01"
  ],
  "tsutaya": [
    "2026-06-28",
    "2026-06-29",
    "2026-06-30",
    "2026-07-01"
  ]
}