{
  "2ndstreet": [
    "2026-07-03",
    "2026-07-04",
    "2026-07-05",
    "2026-07-06"
  ],
  "bookoff": [
    "2026-07-03",
    "2026-07-04",
    "2026-07-05",
    "2026-07-06"
  ],
  "dosupara": [
    "2026-07-03",
    "2026-07-04",
    "2026-07-05",
    "2026-07-06"
  ],
  "geo": [],
  "geo_mobile": [
    "2026-07-03",
    "2026-07-04",
    "2026-07-05",
    "2026-07-06"
  ],
  "hardoff": [
    "2026-07-03",
    "2026-07-04",
    "2026-07-05",
    "2026-07-06"
  ],
  "iosys": [],
  "janpara": [
    "2026-07-03",
    "2026-07-04",
    "2026-07-05",
    "2026-07-06"
  ],
  "kaitori_itchome": [],
  "kaitori_shouten": [],
  "mobile_ichiban": [],
  "netoff": [],
  "pasoko": [
    "2026-07-03",
    "2026-07-04",
    "2026-07-05",
    "2026-07-06"
  ],
  "sofmap": [
    "2026-07-03",
    "2026-07-04",
    "2026-07-05",
    "2026-07-06"
  ],
  "surugaya": [
    "2026-07-03",
    "2026-07-04",
    "2026-07-05",
    "2026-07-06"
  ],
  "tsutaya": [
    "2026-07-03",
    "2026-07-04",
    "2026-07-05",
    "2026-07-06"
  ]
}