{
  "generated_at": "2026-05-31 23:57 JST",
  "total": 24,
  "by_severity": {
    "high": 0,
    "medium": 20,
    "low": 4
  },
  "by_type": {
    "buyback_surge": 7,
    "buyback_drop": 13,
    "overseas_price_stale": 4
  },
  "alerts": [
    {
      "alert_id": "638432a1-340",
      "alert_type": "buyback_surge",
      "product_name": "iPhone 17 Pro Max 512GB SIMフリー",
      "brand": "",
      "category": "",
      "severity": "medium",
      "title": "買取急騰: iPhone 17 Pro Max 512GB SIMフリー",
      "message": "",
      "product_url": "",
      "action_url": "",
      "action_label": "",
      "detected_at": "2026-05-31 23:57",
      "expires_at": "",
      "source": "buyback_db",
      "data_source": "auto_generated",
      "confidence": "medium"
    },
    {
      "alert_id": "586a2fbe-b57",
      "alert_type": "buyback_surge",
      "product_name": "iPhone 17 Pro Max 256GB SIMフリー",
      "brand": "",
      "category": "",
      "severity": "medium",
      "title": "買取急騰: iPhone 17 Pro Max 256GB SIMフリー",
      "message": "",
      "product_url": "",
      "action_url": "",
      "action_label": "",
      "detected_at": "2026-05-31 23:57",
      "expires_at": "",
      "source": "buyback_db",
      "data_source": "auto_generated",
      "confidence": "medium"
    },
    {
      "alert_id": "75f4e8b2-d05",
      "alert_type": "buyback_surge",
      "product_name": "iPhone 17 Pro 512GB SIMフリー",
      "brand": "",
      "category": "",
      "severity": "medium",
      "title": "買取急騰: iPhone 17 Pro 512GB SIMフリー",
      "message": "",
      "product_url": "",
      "action_url": "",
      "action_label": "",
      "detected_at": "2026-05-31 23:57",
      "expires_at": "",
      "source": "buyback_db",
      "data_source": "auto_generated",
      "confidence": "medium"
    },
    {
      "alert_id": "98e78e72-d5e",
      "alert_type": "buyback_surge",
      "product_name": "iPhone 17 Pro 256GB SIMフリー",
      "brand": "",
      "category": "",
      "severity": "medium",
      "title": "買取急騰: iPhone 17 Pro 256GB SIMフリー",
      "message": "",
      "product_url": "",
      "action_url": "",
      "action_label": "",
      "detected_at": "2026-05-31 23:57",
      "expires_at": "",
      "source": "buyback_db",
      "data_source": "auto_generated",
      "confidence": "medium"
    },
    {
      "alert_id": "139f8a90-b02",
      "alert_type": "buyback_surge",
      "product_name": "PlayStation 5 Pro",
      "brand": "",
      "category": "",
      "severity": "medium",
      "title": "買取急騰: PlayStation 5 Pro",
      "message": "",
      "product_url": "",
      "action_url": "",
      "action_label": "",
      "detected_at": "2026-05-31 23:57",
      "expires_at": "",
      "source": "buyback_db",
      "data_source": "auto_generated",
      "confidence": "medium"
    },
    {
      "alert_id": "7c4103a1-707",
      "alert_type": "buyback_surge",
      "product_name": "Nintendo Switch 2",
      "brand": "",
      "category": "",
      "severity": "medium",
      "title": "買取急騰: Nintendo Switch 2",
      "message": "",
      "product_url": "",
      "action_url": "",
      "action_label": "",
      "detected_at": "2026-05-31 23:57",
      "expires_at": "",
      "source": "buyback_db",
      "data_source": "auto_generated",
      "confidence": "medium"
    },
    {
      "alert_id": "733f9440-5c1",
      "alert_type": "buyback_drop",
      "product_name": "Nintendo Switch 2",
      "brand": "",
      "category": "",
      "severity": "medium",
      "title": "買取急落: Nintendo Switch 2",
      "message": "",
      "product_url": "",
      "action_url": "",
      "action_label": "",
      "detected_at": "2026-05-31 23:57",
      "expires_at": "",
      "source": "buyback_db",
      "data_source": "auto_generated",
      "confidence": "medium"
    },
    {
      "alert_id": "95b66e63-35d",
      "alert_type": "buyback_surge",
      "product_name": "Nintendo Switch 2",
      "brand": "",
      "category": "",
      "severity": "medium",
      "title": "買取急騰: Nintendo Switch 2",
      "message": "",
      "product_url": "",
      "action_url": "",
      "action_label": "",
      "detected_at": "2026-05-31 23:57",
      "expires_at": "",
      "source": "buyback_db",
      "data_source": "auto_generated",
      "confidence": "medium"
    },
    {
      "alert_id": "bb606176-7d9",
      "alert_type": "buyback_drop",
      "product_name": "MacBook Air M4 13インチ",
      "brand": "",
      "category": "",
      "severity": "medium",
      "title": "買取急落: MacBook Air M4 13インチ",
      "message": "",
      "product_url": "",
      "action_url": "",
      "action_label": "",
      "detected_at": "2026-05-31 23:57",
      "expires_at": "",
      "source": "buyback_db",
      "data_source": "auto_generated",
      "confidence": "medium"
    },
    {
      "alert_id": "4b05c597-366",
      "alert_type": "buyback_drop",
      "product_name": "MacBook Air M4 13インチ",
      "brand": "",
      "category": "",
      "severity": "medium",
      "title": "買取急落: MacBook Air M4 13インチ",
      "message": "",
      "product_url": "",
      "action_url": "",
      "action_label": "",
      "detected_at": "2026-05-31 23:57",
      "expires_at": "",
      "source": "buyback_db",
      "data_source": "auto_generated",
      "confidence": "medium"
    },
    {
      "alert_id": "b0c5a010-24b",
      "alert_type": "buyback_drop",
      "product_name": "Mac mini M4",
      "brand": "",
      "category": "",
      "severity": "medium",
      "title": "買取急落: Mac mini M4",
      "message": "",
      "product_url": "",
      "action_url": "",
      "action_label": "",
      "detected_at": "2026-05-31 23:57",
      "expires_at": "",
      "source": "buyback_db",
      "data_source": "auto_generated",
      "confidence": "medium"
    },
    {
      "alert_id": "9c180759-ced",
      "alert_type": "buyback_drop",
      "product_name": "iPhone 17 Pro Max 512GB SIMフリー",
      "brand": "",
      "category": "",
      "severity": "medium",
      "title": "買取急落: iPhone 17 Pro Max 512GB SIMフリー",
      "message": "",
      "product_url": "",
      "action_url": "",
      "action_label": "",
      "detected_at": "2026-05-31 23:57",
      "expires_at": "",
      "source": "buyback_db",
      "data_source": "auto_generated",
      "confidence": "medium"
    },
    {
      "alert_id": "b348462d-f4d",
      "alert_type": "buyback_drop",
      "product_name": "iPhone 17 Pro Max 256GB SIMフリー",
      "brand": "",
      "category": "",
      "severity": "medium",
      "title": "買取急落: iPhone 17 Pro Max 256GB SIMフリー",
      "message": "",
      "product_url": "",
      "action_url": "",
      "action_label": "",
      "detected_at": "2026-05-31 23:57",
      "expires_at": "",
      "source": "buyback_db",
      "data_source": "auto_generated",
      "confidence": "medium"
    },
    {
      "alert_id": "160cb53c-2e9",
      "alert_type": "buyback_drop",
      "product_name": "iPhone 17 Pro 512GB SIMフリー",
      "brand": "",
      "category": "",
      "severity": "medium",
      "title": "買取急落: iPhone 17 Pro 512GB SIMフリー",
      "message": "",
      "product_url": "",
      "action_url": "",
      "action_label": "",
      "detected_at": "2026-05-31 23:57",
      "expires_at": "",
      "source": "buyback_db",
      "data_source": "auto_generated",
      "confidence": "medium"
    },
    {
      "alert_id": "a221cb2a-0ed",
      "alert_type": "buyback_drop",
      "product_name": "iPhone 17 Pro 256GB SIMフリー",
      "brand": "",
      "category": "",
      "severity": "medium",
      "title": "買取急落: iPhone 17 Pro 256GB SIMフリー",
      "message": "",
      "product_url": "",
      "action_url": "",
      "action_label": "",
      "detected_at": "2026-05-31 23:57",
      "expires_at": "",
      "source": "buyback_db",
      "data_source": "auto_generated",
      "confidence": "medium"
    },
    {
      "alert_id": "73787647-a21",
      "alert_type": "buyback_drop",
      "product_name": "iPhone 17 256GB SIMフリー",
      "brand": "",
      "category": "",
      "severity": "medium",
      "title": "買取急落: iPhone 17 256GB SIMフリー",
      "message": "",
      "product_url": "",
      "action_url": "",
      "action_label": "",
      "detected_at": "2026-05-31 23:57",
      "expires_at": "",
      "source": "buyback_db",
      "data_source": "auto_generated",
      "confidence": "medium"
    },
    {
      "alert_id": "34047535-34c",
      "alert_type": "buyback_drop",
      "product_name": "iPhone 17 256GB SIMフリー",
      "brand": "",
      "category": "",
      "severity": "medium",
      "title": "買取急落: iPhone 17 256GB SIMフリー",
      "message": "",
      "product_url": "",
      "action_url": "",
      "action_label": "",
      "detected_at": "2026-05-31 23:57",
      "expires_at": "",
      "source": "buyback_db",
      "data_source": "auto_generated",
      "confidence": "medium"
    },
    {
      "alert_id": "2386ef9e-777",
      "alert_type": "buyback_drop",
      "product_name": "iPhone 16 Pro 256GB SIMフリー",
      "brand": "",
      "category": "",
      "severity": "medium",
      "title": "買取急落: iPhone 16 Pro 256GB SIMフリー",
      "message": "",
      "product_url": "",
      "action_url": "",
      "action_label": "",
      "detected_at": "2026-05-31 23:57",
      "expires_at": "",
      "source": "buyback_db",
      "data_source": "auto_generated",
      "confidence": "medium"
    },
    {
      "alert_id": "33a9d3ab-cc6",
      "alert_type": "buyback_drop",
      "product_name": "iPhone 16 Pro 256GB SIMフリー",
      "brand": "",
      "category": "",
      "severity": "medium",
      "title": "買取急落: iPhone 16 Pro 256GB SIMフリー",
      "message": "",
      "product_url": "",
      "action_url": "",
      "action_label": "",
      "detected_at": "2026-05-31 23:57",
      "expires_at": "",
      "source": "buyback_db",
      "data_source": "auto_generated",
      "confidence": "medium"
    },
    {
      "alert_id": "3be425ce-ac9",
      "alert_type": "buyback_drop",
      "product_name": "iPad Pro M4 11インチ",
      "brand": "",
      "category": "",
      "severity": "medium",
      "title": "買取急落: iPad Pro M4 11インチ",
      "message": "",
      "product_url": "",
      "action_url": "",
      "action_label": "",
      "detected_at": "2026-05-31 23:57",
      "expires_at": "",
      "source": "buyback_db",
      "data_source": "auto_generated",
      "confidence": "medium"
    },
    {
      "alert_id": "be7bc38f-7f5",
      "alert_type": "overseas_price_stale",
      "product_name": "FUJIFILM X100VI",
      "brand": "",
      "category": "",
      "severity": "low",
      "title": "海外価格データ更新が必要: FUJIFILM X100VI",
      "message": "eBay ¥509,588 / 最終取得: 2026-05-28T10:00 (48h超) / confidence=medium",
      "product_url": "https://www.ebay.com/sch/i.html?_nkw=FUJIFILM+X100VI&LH_Sold=1&LH_Complete=1",
      "action_url": "",
      "action_label": "",
      "detected_at": "2026-05-31 23:57",
      "expires_at": "",
      "source": "overseas_prices_json",
      "data_source": "auto_generated",
      "confidence": "medium"
    },
    {
      "alert_id": "619ff271-309",
      "alert_type": "overseas_price_stale",
      "product_name": "RICOH GR IIIx",
      "brand": "",
      "category": "",
      "severity": "low",
      "title": "海外価格データ更新が必要: RICOH GR IIIx",
      "message": "eBay ¥222,945 / 最終取得: 2026-05-28T10:00 (48h超) / confidence=medium",
      "product_url": "https://www.ebay.com/sch/i.html?_nkw=Ricoh+GR+IIIx&LH_Sold=1&LH_Complete=1",
      "action_url": "",
      "action_label": "",
      "detected_at": "2026-05-31 23:57",
      "expires_at": "",
      "source": "overseas_prices_json",
      "data_source": "auto_generated",
      "confidence": "medium"
    },
    {
      "alert_id": "3c25594f-ea5",
      "alert_type": "overseas_price_stale",
      "product_name": "RICOH GR IV",
      "brand": "",
      "category": "",
      "severity": "low",
      "title": "海外価格データ更新が必要: RICOH GR IV",
      "message": "eBay ¥294,606 / 最終取得: 2026-05-28T10:00 (48h超) / confidence=medium",
      "product_url": "https://www.ebay.com/sch/i.html?_nkw=Ricoh+GR+IV&LH_Sold=1&LH_Complete=1",
      "action_url": "",
      "action_label": "",
      "detected_at": "2026-05-31 23:57",
      "expires_at": "",
      "source": "overseas_prices_json",
      "data_source": "auto_generated",
      "confidence": "medium"
    },
    {
      "alert_id": "ba636a63-87e",
      "alert_type": "overseas_price_stale",
      "product_name": "Nintendo Switch 2",
      "brand": "",
      "category": "",
      "severity": "low",
      "title": "海外価格データ更新が必要: Nintendo Switch 2",
      "message": "eBay ¥76,438 / 最終取得: 2026-05-28T10:00 (48h超) / confidence=medium",
      "product_url": "https://www.ebay.com/sch/i.html?_nkw=Nintendo+Switch+2&LH_Sold=1&LH_Complete=1",
      "action_url": "",
      "action_label": "",
      "detected_at": "2026-05-31 23:57",
      "expires_at": "",
      "source": "overseas_prices_json",
      "data_source": "auto_generated",
      "confidence": "medium"
    }
  ]
}